README
setup.py
nyc_crime_map/__init__.py
nyc_crime_map/args.py
nyc_crime_map/download.py
nyc_crime_map/serialize.py
nyc_crime_map.egg-info/PKG-INFO
nyc_crime_map.egg-info/SOURCES.txt
nyc_crime_map.egg-info/dependency_links.txt
nyc_crime_map.egg-info/entry_points.txt
nyc_crime_map.egg-info/pbr.json
nyc_crime_map.egg-info/requires.txt
nyc_crime_map.egg-info/top_level.txt