Metadata-Version: 1.1
Name: nyc-crime-map
Version: 0.3.2
Summary: Get data from the crime map
Home-page: http://thomaslevine.com/!/nyc-crime-map/
Author: Thomas Levine
Author-email: _@thomaslevine.com
License: AGPL
Platform: UNKNOWN
Classifier: Programming Language :: Python :: 3.4
